{"message":"ok","data":[{"id":"244","type":"ENG-W vs PAK-W","tournament_name":"3rd ODI","category_id":"3","team_a_name":"England","team_a_logo":"https:\/\/upload.wikimedia.org\/wikipedia\/en\/thumb\/b\/be\/Flag_of_England.svg\/100px-Flag_of_England.svg.png","team_b_name":"Pakistan","team_b_logo":"https:\/\/upload.wikimedia.org\/wikipedia\/commons\/thumb\/3\/32\/Flag_of_Pakistan.svg\/100px-Flag_of_Pakistan.svg.png","url":"PT13Tw==","time":"29.05.2024, 18:00","order":"17","highlight":"0","published":"1","created_at":"2024-04-20 04:30:48","updated_at":"2024-05-29 02:48:32","flussonic":"0"}]}